{
  "appId": "com.madeasy.browser",
  "productName": "MadEasy Browser",
  "directories": {
    "output": "dist-electron"
  },
  "files": [
    "dist/**/*",
    "electron/**/*",
    "package.json"
  ],
  "mac": {
    "category": "public.app-category.productivity",
    "icon": "attached_assets/icon.icns",
    "target": [
      {
        "target": "dmg",
        "arch": ["x64", "arm64"]
      },
      {
        "target": "zip",
        "arch": ["x64", "arm64"]
      }
    ],
    "hardenedRuntime": true,
    "gatekeeperAssess": false,
    "entitlements": "build/entitlements.mac.plist",
    "entitlementsInherit": "build/entitlements.mac.plist",
    "notarize": {
      "teamId": "YOUR_TEAM_ID"
    }
  },
  "win": {
    "target": "nsis",
    "icon": "attached_assets/icon.ico"
  },
  "linux": {
    "target": "AppImage",
    "icon": "attached_assets/icon.png",
    "category": "Network"
  },
  "nsis": {
    "oneClick": false,
    "allowToChangeInstallationDirectory": true
  }
}